{"is_source_file": false, "format": "", "description": "", "external_files": [], "external_methods": [], "published": [], "classes": [], "methods": [], "calls": [], "search-terms": ["checkstyle", "config", "xml", "rules", "formatter"], "state": 2, "file_id": 15, "knowledge_revision": 35, "git_revision": "fc6a3dd883ffe3d78f996dee6c658d1e90f0e041", "hash": "0e802116eee12d0a6fd53ae81f89ca3a", "format-version": 4, "code-base-name": "notes_backend", "filename": "notes_backend/config/checkstyle/checkstyle.xml", "revision_history": [{"35": "fc6a3dd883ffe3d78f996dee6c658d1e90f0e041"}]}